Verilog/Week-2/inlab/task1/module.v
module dFlipFlop (
    input clk,
    input d,
    output reg q
);
    // Register logic must be written in an always block
    // This block is triggered on the rising edge of the clock
    always @(posedge clk) begin
        q = d;
    end

endmodule

module buffer (
    input d,
    output wire q
);

   assign q = d;

endmodule

Verilog/Week-2/inlab/task1/testbench.v
module tb_compare_wire_reg;
    reg clk;
    reg d;
    wire q_comb;
    wire q_ff;

    buffer u_comb (.d(d), .q(q_comb));
    dFlipFlop u_ff (.clk(clk), .d(d), .q(q_ff));

    // Clock generation
    initial clk = 0;
    always #5 clk = ~clk;  // 10ns clock

    initial begin
        $dumpfile("wave.vcd");   // output VCD file
        $dumpvars(0, tb_compare_wire_reg);  // dump all variables in tb_compare_wire_reg
        $display("Time | clk d | comb q | flipflop q");
        $monitor("%4t |  %b   %b |    %b     |     %b", $time, clk, d, q_comb, q_ff);
        
        d = 0; #7;
        d = 1; #10;
        d = 0; #10;
        d = 1; #10;
        $finish;
    end
endmodule

Verilog/Week-2/inlab/task1/wave.vcd
$date
	Tue Aug 12 15:47:22 2025
$end
$version
	Icarus Verilog
$end
$timescale
	1s
$end
$scope module tb_compare_wire_reg $end
$var wire 1 ! q_ff $end
$var wire 1 " q_comb $end
$var reg 1 # clk $end
$var reg 1 $ d $end
$scope module u_comb $end
$var wire 1 $ d $end
$var wire 1 " q $end
$upscope $end
$scope module u_ff $end
$var wire 1 # clk $end
$var wire 1 $ d $end
$var reg 1 ! q $end
$upscope $end
$upscope $end
$enddefinitions $end
$comment Show the parameter values. $end
$dumpall
$end
#0
$dumpvars
0$
0#
0"
x!
$end
#5
0!
1#
#7
1"
1$
#10
0#
#15
1!
1#
#17
0"
0$
#20
0#
#25
0!
1#
#27
1"
1$
#30
0#
#35
1!
1#
