Verilog/Week-1/task1/module.v
module adder (
    input a,
    input b,
    input cin,
    output sum,
    output cout
);
    // Fill in the logic for the adder
    assign cout = (a&b)|(cin&a)|(cin&b);
    assign sum = (!a&b&!cin)|(!a&!b&cin)|(a&b&cin)|(a&!b&!cin);
endmodule

Verilog/Week-1/task1/tb_module.v
module tb_adder;
    reg a, b, cin;
    wire sum, cout;

    adder uut (
        .a(a), .b(b), .cin(cin),
        .sum(sum), .cout(cout)
    );

    integer i;

    initial begin
        $dumpfile("wave.vcd");   // output VCD file
        $dumpvars(0, tb_adder);  // dump all variables in tb_adder
        $display("a b cin | cout sum");
        for (i = 0; i < 8; i = i + 1) begin
            {a, b, cin} = i;
            #10 $display("%b %b  %b  |  %b    %b", a, b, cin, cout, sum);
        end
    end
endmodule

Verilog/Week-1/task1/wave.vcd
$date
	Tue Aug  5 14:22:45 2025
$end
$version
	Icarus Verilog
$end
$timescale
	1s
$end
$scope module tb_adder $end
$var wire 1 ! sum $end
$var wire 1 " cout $end
$var reg 1 # a $end
$var reg 1 $ b $end
$var reg 1 % cin $end
$var integer 32 & i [31:0] $end
$scope module uut $end
$var wire 1 # a $end
$var wire 1 $ b $end
$var wire 1 % cin $end
$var wire 1 " cout $end
$var wire 1 ! sum $end
$upscope $end
$upscope $end
$enddefinitions $end
$comment Show the parameter values. $end
$dumpall
$end
#0
$dumpvars
b0 &
0%
0$
0#
0"
0!
$end
#10
1!
1%
b1 &
#20
1!
1$
0%
b10 &
#30
0!
1"
1%
b11 &
#40
1!
0"
1#
0$
0%
b100 &
#50
1"
0!
1%
b101 &
#60
0!
1$
0%
b110 &
#70
1!
1%
b111 &
#80
b1000 &
