Verilog/Week-2/inlab/task2/buggy_modules.v
module shiftReg1 (
    input clk,
    input rst,
    input din,
    output [3:0] q
);
    reg [3:0] shiftReg;  

    assign q = shiftReg;

    always @(posedge clk) begin
        if (rst)
            shiftReg <= 4'b0000;
        else
            shiftReg <= {shiftReg[2:0], din};
    end
endmodule

module shiftReg2 (
    input clk,  
    input rst,
    input din,
    output [3:0] q
);
    reg [3:0] shiftReg;

    assign q = shiftReg;

    always @(posedge clk) begin
        if (rst)
            shiftReg <= 4'b0000;
        else
            shiftReg <= {din, shiftReg[3:1]};
    end
endmodule

module shiftReg3 (
    input clk,
    input rst,
    input din,
    output [3:0] q
);
    reg [3:0] shiftReg;

    assign q = shiftReg;
    always @(posedge clk) begin
    shiftReg <= rst ? 4'b0000 : {shiftReg[2:0], din}; 
    end
endmodule

module shiftReg4 (
    input clk,
    input rst,
    input din,
    output [3:0] q
);
    reg [3:0] shiftReg;

    assign q = shiftReg;
    always @(posedge clk) begin
        if (rst == 1'b1) begin
            shiftReg <= 4'b0000;
        end
        shiftReg <= {shiftReg[2:0], din}; 
    end
endmodule

module shiftReg (
    input clk,
    input rst,
    input din,
    output [3:0] q
);
    reg [3:0] shiftReg;

    assign q = shiftReg;
    always @(posedge clk) begin
    shiftReg <= rst ? 4'b0000 : {shiftReg[2:0], din}; 
    end
endmodule

Verilog/Week-2/inlab/task2/testbench.v
module tb_shift_reg;
    reg clk, rst, din;
    wire [3:0] q;

    shiftReg uut (.clk(clk), .rst(rst), .din(din), .q(q));  // Change module name per test

    always #5 clk = ~clk;

    initial begin
        clk = 0; rst = 1; din = 0;
        $dumpfile("wave.vcd");
        $dumpvars(0, tb_shift_reg);
        $monitor("Time: %0t, clk: %b, rst: %b, din: %b, q: %b", $time, clk, rst, din, q);

        #10 rst = 0;

        din = 1; #10;
        din = 0; #10;
        din = 1; #10;
        din = 1; #10;

        din = 0; #20;

        $finish;
    end
endmodule

Verilog/Week-2/inlab/task2/wave.vcd
$date
	Tue Aug 12 16:31:45 2025
$end
$version
	Icarus Verilog
$end
$timescale
	1s
$end
$scope module tb_shift_reg $end
$var wire 4 ! q [3:0] $end
$var reg 1 " clk $end
$var reg 1 # din $end
$var reg 1 $ rst $end
$scope module uut $end
$var wire 1 " clk $end
$var wire 1 # din $end
$var wire 4 % q [3:0] $end
$var wire 1 $ rst $end
$var reg 4 & shiftReg [3:0] $end
$upscope $end
$upscope $end
$enddefinitions $end
$comment Show the parameter values. $end
$dumpall
$end
#0
$dumpvars
bx &
bx %
1$
0#
0"
bx !
$end
#5
b0 !
b0 %
b0 &
1"
#10
0"
1#
0$
#15
b1 !
b1 %
b1 &
1"
#20
0"
0#
#25
b10 !
b10 %
b10 &
1"
#30
0"
1#
#35
b101 !
b101 %
b101 &
1"
#40
0"
#45
b1011 !
b1011 %
b1011 &
1"
#50
0"
0#
#55
b110 !
b110 %
b110 &
1"
#60
0"
#65
b1100 !
b1100 %
b1100 &
1"
